modellingOftheProcessor/alu.v
`timescale 1ns/1ps
module alu(
    input  wire [5:0]  opcode,
    input  wire [31:0] a,
    input  wire [31:0] b,
    output reg  [31:0] result
);
    // Opcodes
    localparam ADD   = 6'b000000,
               SUB   = 6'b000001,
               AND   = 6'b000010,
               SLT   = 6'b000011,
               MUL   = 6'b000100,
               OR    = 6'b000101,
               ADDI  = 6'b001010,
               SUBI  = 6'b001011,
               SLTI  = 6'b001100,
               LW    = 6'b001101,
               SW    = 6'b001110,
               BNEQZ = 6'b001111,
               BEQZ  = 6'b010000;

    always @* begin
        case (opcode)
            ADD, ADDI, LW, SW, BNEQZ, BEQZ: result = a + b;
            SUB, SUBI:                      result = a - b;
            AND:                            result = a & b;
            OR:                             result = a | b;
            SLT, SLTI:                      result = (a < b) ? 32'd1 : 32'd0;
            MUL:                            result = a * b;
            default:                        result = 32'hxxxxxxxx;
        endcase
    end
endmodule

modellingOftheProcessor/memory_interface.v
`timescale 1ns/1ps
module memory_interface(
    input  wire        clock,
    input  wire [31:0] instr_addr,
    output wire [31:0] instr_out,
    input  wire [31:0] data_addr,
    input  wire [31:0] data_in,
    output wire [31:0] data_out,
    input  wire        data_we
);
    reg [31:0] mem[0:1023];

    integer i;
    initial begin
        for (i = 0; i < 1024; i = i + 1) begin
            mem[i] = 32'd0;
        end
    end

    assign instr_out = mem[instr_addr];
    assign data_out  = mem[data_addr];

    always @(posedge clock) begin
        if (data_we) begin
            mem[data_addr] <= data_in;
        end
    end
endmodule

modellingOftheProcessor/regfile.v
`timescale 1ns/1ps
module regfile(
    input  wire        clock,
    input  wire        we,
    input  wire [4:0]  ra1,
    input  wire [4:0]  ra2,
    input  wire [4:0]  wa,
    input  wire [31:0] wd,
    output wire [31:0] rd1,
    output wire [31:0] rd2
);
    reg [31:0] regs[0:31];

    integer i;
    initial begin
        for (i = 0; i < 32; i = i + 1) begin
            regs[i] = 32'd0;
        end
    end

    assign rd1 = (ra1 == 5'd0) ? 32'd0 : regs[ra1];
    assign rd2 = (ra2 == 5'd0) ? 32'd0 : regs[ra2];

    always @(posedge clock) begin
        if (we && (wa != 5'd0)) begin
            regs[wa] <= wd;
        end
    end
endmodule

modellingOftheProcessor/control_unit.v
`timescale 1ns/1ps
module control_unit(
    input  wire [5:0] opcode,
    output reg  [2:0] instr_type
);
    // Opcodes
    localparam ADD   = 6'b000000,
               SUB   = 6'b000001,
               AND   = 6'b000010,
               SLT   = 6'b000011,
               MUL   = 6'b000100,
               OR    = 6'b000101,
               ADDI  = 6'b001010,
               SUBI  = 6'b001011,
               SLTI  = 6'b001100,
               LW    = 6'b001101,
               SW    = 6'b001110,
               BNEQZ = 6'b001111,
               BEQZ  = 6'b010000,
               HLT   = 6'b111111;

    // Instruction type tags
    localparam RR_ALU = 3'b000,
               RM_ALU = 3'b001,
               LOAD   = 3'b010,
               STORE  = 3'b011,
               BRANCH = 3'b100,
               HALT   = 3'b101;

    always @* begin
        case (opcode)
            ADD, SUB, AND, OR, SLT, MUL: instr_type = RR_ALU;
            ADDI, SUBI, SLTI:            instr_type = RM_ALU;
            LW:                          instr_type = LOAD;
            SW:                          instr_type = STORE;
            BNEQZ, BEQZ:                 instr_type = BRANCH;
            HLT:                         instr_type = HALT;
            default:                     instr_type = HALT;
        endcase
    end
endmodule

modellingOftheProcessor/mips.v
// Simple pipelined MIPS-like processor based on lecture transcript
`timescale 1ns/1ps
module mips(input clock1, input clock2);
    // Program counter
    reg [31:0] PC;

    // IF/ID pipeline registers
    reg [31:0] IF_ID_IR, IF_ID_NPC;

    // ID/EX pipeline registers
    reg [31:0] ID_EX_IR, ID_EX_NPC, ID_EX_A, ID_EX_B, ID_EX_IMM;
    reg [2:0]  ID_EX_type;

    // EX/MEM pipeline registers
    reg [31:0] EX_MEM_IR, EX_MEM_ALUOut, EX_MEM_B;
    reg        EX_MEM_cond;
    reg [2:0]  EX_MEM_type;

    // MEM/WB pipeline registers
    reg [31:0] MEM_WB_IR, MEM_WB_ALUOut, MEM_WB_LMD;
    reg [2:0]  MEM_WB_type;

    // Opcodes
    parameter ADD   = 6'b000000,
              SUB   = 6'b000001,
              AND   = 6'b000010,
              SLT   = 6'b000011,
              MUL   = 6'b000100,
              OR    = 6'b000101,
              ADDI  = 6'b001010,
              SUBI  = 6'b001011,
              SLTI  = 6'b001100,
              LW    = 6'b001101,
              SW    = 6'b001110,
              BNEQZ = 6'b001111,
              BEQZ  = 6'b010000,
              HLT   = 6'b111111;

    // Instruction type tags
    parameter RR_ALU = 3'b000,
              RM_ALU = 3'b001,
              LOAD   = 3'b010,
              STORE  = 3'b011,
              BRANCH = 3'b100,
              HALT   = 3'b101;

    // Control flags
    reg halted, taken_branch;

    // Decode / datapath modules
    wire [2:0]  dec_type;
    wire [31:0] rf_rd1, rf_rd2;

    wire        rf_we;
    wire [4:0]  rf_wa;
    wire [31:0] rf_wd;

    wire        branch_taken;
    wire [31:0] ifetch_addr;
    wire [31:0] instr_word;

    wire        mem_we;
    wire [31:0] mem_data_out;

    wire [31:0] alu_a, alu_b, alu_out;

    control_unit cu(
        .opcode(IF_ID_IR[31:26]),
        .instr_type(dec_type)
    );

    regfile rf(
        .clock(clock1),
        .we(rf_we),
        .ra1(IF_ID_IR[25:21]),
        .ra2(IF_ID_IR[20:16]),
        .wa(rf_wa),
        .wd(rf_wd),
        .rd1(rf_rd1),
        .rd2(rf_rd2)
    );

    memory_interface memory(
        .clock(clock2),
        .instr_addr(ifetch_addr),
        .instr_out(instr_word),
        .data_addr(EX_MEM_ALUOut),
        .data_in(EX_MEM_B),
        .data_out(mem_data_out),
        .data_we(mem_we)
    );

    alu alu_unit(
        .opcode(ID_EX_IR[31:26]),
        .a(alu_a),
        .b(alu_b),
        .result(alu_out)
    );

    assign branch_taken =
        ((EX_MEM_IR[31:26] === BEQZ)  && (EX_MEM_cond === 1'b1)) ||
        ((EX_MEM_IR[31:26] === BNEQZ) && (EX_MEM_cond === 1'b0));

    assign ifetch_addr = branch_taken ? EX_MEM_ALUOut : PC;

    assign alu_a = (ID_EX_type == BRANCH) ? ID_EX_NPC : ID_EX_A;
    assign alu_b = (ID_EX_type == RR_ALU) ? ID_EX_B : ID_EX_IMM;

    assign mem_we = (!halted) && (EX_MEM_type == STORE) && (!taken_branch);

    assign rf_wa = (MEM_WB_type == RR_ALU) ? MEM_WB_IR[15:11] : MEM_WB_IR[20:16];
    assign rf_wd = (MEM_WB_type == LOAD) ? MEM_WB_LMD : MEM_WB_ALUOut;
    assign rf_we =
        (!taken_branch) &&
        ((MEM_WB_type == RR_ALU) || (MEM_WB_type == RM_ALU) || (MEM_WB_type == LOAD)) &&
        (rf_wa != 5'd0);

    initial begin
        PC = 0;
        halted = 0;
        taken_branch = 0;
    end

    // Instruction Fetch
    always @(posedge clock1) begin
        if (!halted) begin
            IF_ID_IR  <= instr_word;
            IF_ID_NPC <= ifetch_addr + 1;
            PC        <= ifetch_addr + 1;
            taken_branch <= branch_taken;
        end
    end

    // Instruction Decode
    always @(posedge clock2) begin
        if (!halted) begin
            ID_EX_NPC <= IF_ID_NPC;
            ID_EX_IR  <= IF_ID_IR;

            // Register operand fetch with R0 hardwired to zero
            ID_EX_A <= rf_rd1;
            ID_EX_B <= rf_rd2;

            // Sign-extended immediate
            ID_EX_IMM <= {{16{IF_ID_IR[15]}}, IF_ID_IR[15:0]};

            // Determine instruction type
            ID_EX_type <= dec_type;
        end
    end

    // Execute
    always @(posedge clock1) begin
        if (!halted) begin
            EX_MEM_type <= ID_EX_type;
            EX_MEM_IR   <= ID_EX_IR;
            EX_MEM_ALUOut <= (ID_EX_type == HALT) ? 32'd0 : alu_out;
            EX_MEM_B      <= ID_EX_B;
            EX_MEM_cond   <= (ID_EX_A == 0);//its checking the condition , here, to branch or not .
        end
    end

    // Memory access
    always @(posedge clock2) begin
        if (!halted) begin
            MEM_WB_type   <= EX_MEM_type;
            MEM_WB_IR     <= EX_MEM_IR;
            MEM_WB_ALUOut <= EX_MEM_ALUOut;

            case (EX_MEM_type)
                LOAD: begin
                    MEM_WB_LMD <= mem_data_out;
                end
                default: ;
            endcase
        end
    end

    // Write back
    always @(posedge clock1) begin
        if (!taken_branch) begin
            case (MEM_WB_type)
                HALT: halted <= 1'b1;
                default: ;
            endcase
        end
    end
endmodule

modellingOftheProcessor/tb_factorial.v
`timescale 1ns/1ps

module tb_factorial;
    reg clock1, clock2;
    mips uut(.clock1(clock1), .clock2(clock2));

    integer k;
    reg init_done;

    // Core pipeline/debug signals (flattened into TB scope for clean VCDs).
    wire [31:0] PC = uut.PC;
    wire [31:0] ifetch_addr = uut.ifetch_addr;
    wire [31:0] instr_word = uut.instr_word;

    wire [31:0] IF_ID_IR = uut.IF_ID_IR;
    wire [31:0] IF_ID_NPC = uut.IF_ID_NPC;

    wire [31:0] ID_EX_IR = uut.ID_EX_IR;
    wire [31:0] ID_EX_NPC = uut.ID_EX_NPC;
    wire [31:0] ID_EX_A = uut.ID_EX_A;
    wire [31:0] ID_EX_B = uut.ID_EX_B;
    wire [31:0] ID_EX_IMM = uut.ID_EX_IMM;
    wire [2:0]  ID_EX_type = uut.ID_EX_type;

    wire [31:0] alu_a = uut.alu_a;
    wire [31:0] alu_b = uut.alu_b;
    wire [31:0] alu_out = uut.alu_out;

    wire [31:0] EX_MEM_IR = uut.EX_MEM_IR;
    wire [31:0] EX_MEM_ALUOut = uut.EX_MEM_ALUOut;
    wire [31:0] EX_MEM_B = uut.EX_MEM_B;
    wire        EX_MEM_cond = uut.EX_MEM_cond;
    wire [2:0]  EX_MEM_type = uut.EX_MEM_type;

    wire        mem_we = uut.mem_we;
    wire [31:0] mem_data_out = uut.mem_data_out;

    wire [31:0] MEM_WB_IR = uut.MEM_WB_IR;
    wire [31:0] MEM_WB_ALUOut = uut.MEM_WB_ALUOut;
    wire [31:0] MEM_WB_LMD = uut.MEM_WB_LMD;
    wire [2:0]  MEM_WB_type = uut.MEM_WB_type;

    wire        rf_we = uut.rf_we;
    wire [4:0]  rf_wa = uut.rf_wa;
    wire [31:0] rf_wd = uut.rf_wd;

    wire        branch_taken = uut.branch_taken;
    wire        taken_branch = uut.taken_branch;
    wire        halted = uut.halted;

    // Waveform-friendly aliases (avoid dumping array elements directly).
    wire [31:0] R0  = uut.rf.regs[0];
    wire [31:0] R2  = uut.rf.regs[2];
    wire [31:0] R3  = uut.rf.regs[3];
    wire [31:0] R7  = uut.rf.regs[7];
    wire [31:0] R10 = uut.rf.regs[10];

    wire [31:0] IMEM0  = uut.memory.mem[0];
    wire [31:0] IMEM1  = uut.memory.mem[1];
    wire [31:0] IMEM2  = uut.memory.mem[2];
    wire [31:0] IMEM3  = uut.memory.mem[3];
    wire [31:0] IMEM4  = uut.memory.mem[4];
    wire [31:0] IMEM5  = uut.memory.mem[5];
    wire [31:0] IMEM6  = uut.memory.mem[6];
    wire [31:0] IMEM7  = uut.memory.mem[7];
    wire [31:0] IMEM8  = uut.memory.mem[8];
    wire [31:0] IMEM9  = uut.memory.mem[9];
    wire [31:0] IMEM10 = uut.memory.mem[10];

    wire [31:0] MEM198 = uut.memory.mem[198];
    wire [31:0] MEM200 = uut.memory.mem[200];

    initial begin
        clock1 = 0; clock2 = 0;
        wait (init_done);
        repeat (200) begin
            #5 clock1 = 1; #5 clock1 = 0;
            #5 clock2 = 1; #5 clock2 = 0;
        end
    end

    initial begin
        init_done = 0;
        #0;
        for (k = 0; k < 32; k = k + 1) begin
            uut.rf.regs[k] = k;
        end

        // Program to compute factorial of the value stored at Mem[200]
        uut.memory.mem[0]  = 32'h280a00c8; // ADDI R10, R0, 200
        uut.memory.mem[1]  = 32'h28020001; // ADDI R2,  R0, 1 (accumulator)
        uut.memory.mem[2]  = 32'h35430000; // LW   R3, 0(R10) load N
        uut.memory.mem[3]  = 32'h14e73800; // OR   R7, R7, R7 (dummy)
        uut.memory.mem[4]  = 32'h10431000; // MUL  R2, R3, R2
        uut.memory.mem[5]  = 32'h14e73800; // OR   R7, R7, R7 (dummy)
        uut.memory.mem[6]  = 32'h2c630001; // SUBI R3, R3, 1
        uut.memory.mem[7]  = 32'h14e73800; // OR   R7, R7, R7 (dummy)
        uut.memory.mem[8]  = 32'h3c60fffb; // BNEQZ R3, loop (-5)
        uut.memory.mem[9]  = 32'h3942fffe; // SW   R2, -2(R10)
        uut.memory.mem[10] = 32'hfc000000; // HLT

        // Place input value N at Mem[200]
        uut.memory.mem[200] = 32'd7;

        // Reset PC and flags
        uut.PC = 0; uut.halted = 0; uut.taken_branch = 0;

        // Initialize pipeline regs for cleaner waveforms (avoids X-propagation).
        uut.IF_ID_IR = 0; uut.IF_ID_NPC = 0;
        uut.ID_EX_IR = 0; uut.ID_EX_NPC = 0; uut.ID_EX_A = 0; uut.ID_EX_B = 0; uut.ID_EX_IMM = 0; uut.ID_EX_type = 0;
        uut.EX_MEM_IR = 0; uut.EX_MEM_ALUOut = 0; uut.EX_MEM_B = 0; uut.EX_MEM_cond = 0; uut.EX_MEM_type = 0;
        uut.MEM_WB_IR = 0; uut.MEM_WB_ALUOut = 0; uut.MEM_WB_LMD = 0; uut.MEM_WB_type = 0;

        init_done = 1;

        // Monitor accumulator as it changes
        $monitor("Time=%0t R2=%0d", $time, uut.rf.regs[2]);

        #3000;
        $display("Mem[200]: %0d", uut.memory.mem[200]);
        $display("Mem[198]: %0d", uut.memory.mem[198]);
        $finish;
    end

    initial begin
        wait (init_done);
        $dumpfile("tb_factorial.vcd");
        $dumpvars(1, tb_factorial);
    end
endmodule

modellingOftheProcessor/artifacts/tb_factorial.vcd
$date
	Mon Feb 02 06:53:18 2026
$end
$version
	Icarus Verilog
$end
$timescale
	1ps
$end
$scope module tb_factorial $end
$var wire 32 ! EX_MEM_ALUOut [31:0] $end
$var wire 32 " EX_MEM_B [31:0] $end
$var wire 32 # EX_MEM_IR [31:0] $end
$var wire 1 $ EX_MEM_cond $end
$var wire 3 % EX_MEM_type [2:0] $end
$var wire 32 & ID_EX_A [31:0] $end
$var wire 32 ' ID_EX_B [31:0] $end
$var wire 32 ( ID_EX_IMM [31:0] $end
$var wire 32 ) ID_EX_IR [31:0] $end
$var wire 32 * ID_EX_NPC [31:0] $end
$var wire 3 + ID_EX_type [2:0] $end
$var wire 32 , IF_ID_IR [31:0] $end
$var wire 32 - IF_ID_NPC [31:0] $end
$var wire 32 . IMEM0 [31:0] $end
$var wire 32 / IMEM1 [31:0] $end
$var wire 32 0 IMEM10 [31:0] $end
$var wire 32 1 IMEM2 [31:0] $end
$var wire 32 2 IMEM3 [31:0] $end
$var wire 32 3 IMEM4 [31:0] $end
$var wire 32 4 IMEM5 [31:0] $end
$var wire 32 5 IMEM6 [31:0] $end
$var wire 32 6 IMEM7 [31:0] $end
$var wire 32 7 IMEM8 [31:0] $end
$var wire 32 8 IMEM9 [31:0] $end
$var wire 32 9 MEM198 [31:0] $end
$var wire 32 : MEM200 [31:0] $end
$var wire 32 ; MEM_WB_ALUOut [31:0] $end
$var wire 32 < MEM_WB_IR [31:0] $end
$var wire 32 = MEM_WB_LMD [31:0] $end
$var wire 3 > MEM_WB_type [2:0] $end
$var wire 32 ? PC [31:0] $end
$var wire 32 @ R0 [31:0] $end
$var wire 32 A R10 [31:0] $end
$var wire 32 B R2 [31:0] $end
$var wire 32 C R3 [31:0] $end
$var wire 32 D R7 [31:0] $end
$var wire 32 E alu_a [31:0] $end
$var wire 32 F alu_b [31:0] $end
$var wire 32 G alu_out [31:0] $end
$var wire 1 H branch_taken $end
$var wire 1 I halted $end
$var wire 32 J ifetch_addr [31:0] $end
$var wire 32 K instr_word [31:0] $end
$var wire 32 L mem_data_out [31:0] $end
$var wire 1 M mem_we $end
$var wire 5 N rf_wa [4:0] $end
$var wire 32 O rf_wd [31:0] $end
$var wire 1 P rf_we $end
$var wire 1 Q taken_branch $end
$var reg 1 R clock1 $end
$var reg 1 S clock2 $end
$var reg 1 T init_done $end
$var integer 32 U k [31:0] $end
$upscope $end
$enddefinitions $end
$comment Show the parameter values. $end
$dumpall
$end
#0
$dumpvars
b100000 U
1T
0S
0R
0Q
0P
b0 O
b0 N
0M
b101000000010100000000011001000 L
b101000000010100000000011001000 K
b0 J
0I
0H
b0 G
b0 F
b0 E
b111 D
b11 C
b10 B
b1010 A
b0 @
b0 ?
b0 >
b0 =
b0 <
b0 ;
b111 :
b0 9
b111001010000101111111111111110 8
b111100011000001111111111111011 7
b10100111001110011100000000000 6
b101100011000110000000000000001 5
b10100111001110011100000000000 4
b10000010000110001000000000000 3
b10100111001110011100000000000 2
b110101010000110000000000000000 1
b11111100000000000000000000000000 0
b101000000000100000000000000001 /
b101000000010100000000011001000 .
b0 -
b0 ,
b0 +
b0 *
b0 )
b0 (
b0 '
b0 &
b0 %
0$
b0 #
b0 "
b0 !
$end
#5000
b101000000000100000000000000001 K
b1 J
b1 ?
b1 -
b101000000010100000000011001000 ,
1$
1R
#10000
0R
#15000
b11001000 G
b11001000 F
b1 +
b11001000 (
b1010 '
b101000000010100000000011001000 )
b1 *
1S
#20000
0S
#25000
b110101010000110000000000000000 K
b10 J
b1010 "
b111 L
b11001000 !
b101000000010100000000011001000 #
b1 %
b10 ?
b10 -
b101000000000100000000000000001 ,
1R
#30000
0R
#35000
1P
b1010 N
b1 G
b11001000 O
b1 F
b11001000 ;
b101000000010100000000011001000 <
b1 >
b1 (
b10 '
b101000000000100000000000000001 )
b10 *
1S
#40000
0S
#45000
b10100111001110011100000000000 K
b11 J
b11001000 A
b11 ?
b11 -
b110101010000110000000000000000 ,
b10 "
b101000000000100000000000000001 L
b1 !
b101000000000100000000000000001 #
1R
#50000
0R
#55000
b11001000 G
b10 N
b0 F
b11001000 E
b1 O
b10 +
b0 (
b11 '
b11001000 &
b110101010000110000000000000000 )
b11 *
b1 ;
b101000000000100000000000000001 <
1S
#60000
0S
#65000
b10000010000110001000000000000 K
b100 J
0$
b11 "
b111 L
b11001000 !
b110101010000110000000000000000 #
b10 %
b100 ?
b100 -
b10100111001110011100000000000 ,
b1 B
1R
#70000
0R
#75000
b11 N
b111 G
b111 O
b111 F
b111 E
b111 =
b11001000 ;
b110101010000110000000000000000 <
b10 >
b0 +
b11100000000000 (
b111 '
b111 &
b10100111001110011100000000000 )
b100 *
1S
#80000
0S
#85000
b10100111001110011100000000000 K
b101 J
b111 C
b101 ?
b101 -
b10000010000110001000000000000 ,
b111 "
b10100111001110011100000000000 L
b111 !
b10100111001110011100000000000 #
b0 %
1R
#90000
0R
#95000
1P
b1 E
b111 N
b1000000000000 (
b1 &
b10000010000110001000000000000 )
b101 *
b111 ;
b10100111001110011100000000000 <
b0 >
1S
#100000
0S
#105000
b101100011000110000000000000001 K
b110 J
b10000010000110001000000000000 #
b110 ?
b110 -
b10100111001110011100000000000 ,
1R
#110000
0R
#115000
b10 N
b111 E
b10000010000110001000000000000 <
b11100000000000 (
b111 &
b10100111001110011100000000000 )
b110 *
1S
#120000
0S
#125000
b10100111001110011100000000000 K
b111 J
b111 B
b111 ?
b111 -
b101100011000110000000000000001 ,
b10100111001110011100000000000 #
1R
#130000
0R
#135000
b110 G
b111 N
b1 F
b1 +
b1 (
b101100011000110000000000000001 )
b111 *
b10100111001110011100000000000 <
1S
#140000
0S
#145000
b111100011000001111111111111011 K
b1000 J
b101100011000110000000000000001 L
b110 !
b101100011000110000000000000001 #
b1 %
b1000 ?
b1000 -
b10100111001110011100000000000 ,
1R
#150000
0R
#155000
b11 N
b111 G
b110 O
b111 F
b110 ;
b101100011000110000000000000001 <
b1 >
b0 +
b11100000000000 (
b10100111001110011100000000000 )
b1000 *
1S
#160000
0S
#165000
b111001010000101111111111111110 K
b1001 J
b110 C
b1001 ?
b1001 -
b111100011000001111111111111011 ,
b10100111001110011100000000000 L
b111 !
b10100111001110011100000000000 #
b0 %
1R
#170000
0R
#175000
b100 G
1P
b11111111111111111111111111111011 F
b1001 E
b111 O
b111 N
b100 +
b11111111111111111111111111111011 (
b0 '
b110 &
b111100011000001111111111111011 )
b1001 *
b111 ;
b10100111001110011100000000000 <
b0 >
1S
#180000
0S
#185000
1H
b10000010000110001000000000000 K
b100 J
b0 "
b10000010000110001000000000000 L
b100 !
b111100011000001111111111111011 #
b100 %
b1010 ?
b1010 -
b111001010000101111111111111110 ,
1R
#190000
0R
#195000
0P
b0 N
b11000110 G
b100 O
b11111111111111111111111111111110 F
b11001000 E
b100 ;
b111100011000001111111111111011 <
b100 >
b11 +
b11111111111111111111111111111110 (
b111 '
b11001000 &
b111001010000101111111111111110 )
b1010 *
1S
#200000
0S
#205000
0H
b10100111001110011100000000000 K
b101 J
1Q
b101 ?
b101 -
b10000010000110001000000000000 ,
b111 "
b0 L
b11000110 !
b111001010000101111111111111110 #
b11 %
1R
#210000
0R
#215000
b101010 G
b10 N
b110 F
b111 E
b11000110 O
b0 +
b1000000000000 (
b110 '
b111 &
b10000010000110001000000000000 )
b101 *
b11000110 ;
b111001010000101111111111111110 <
b11 >
1S
#220000
0S
#225000
0M
b101100011000110000000000000001 K
b110 J
b110 "
b101010 !
b10000010000110001000000000000 #
b0 %
0Q
b110 ?
b110 -
b10100111001110011100000000000 ,
1R
#230000
0R
#235000
1P
b111 G
b101010 O
b10 N
b111 F
b101010 ;
b10000010000110001000000000000 <
b0 >
b11100000000000 (
b111 '
b10100111001110011100000000000 )
b110 *
1S
#240000
0S
#245000
b10100111001110011100000000000 K
b111 J
b101010 B
b111 ?
b111 -
b101100011000110000000000000001 ,
b111 "
b10100111001110011100000000000 L
b111 !
b10100111001110011100000000000 #
1R
#250000
0R
#255000
b101 G
b111 N
b1 F
b110 E
b111 O
b1 +
b1 (
b110 '
b110 &
b101100011000110000000000000001 )
b111 *
b111 ;
b10100111001110011100000000000 <
1S
#260000
0S
#265000
b111100011000001111111111111011 K
b1000 J
b110 "
b101 !
b101100011000110000000000000001 #
b1 %
b1000 ?
b1000 -
b10100111001110011100000000000 ,
1R
#270000
0R
#275000
b11 N
b111 G
b101 O
b111 F
b111 E
b101 ;
b101100011000110000000000000001 <
b1 >
b0 +
b11100000000000 (
b111 '
b111 &
b10100111001110011100000000000 )
b1000 *
1S
#280000
0S
#285000
b111001010000101111111111111110 K
b1001 J
b101 C
b1001 ?
b1001 -
b111100011000001111111111111011 ,
b111 "
b111 !
b10100111001110011100000000000 #
b0 %
1R
#290000
0R
#295000
b100 G
1P
b11111111111111111111111111111011 F
b1001 E
b111 O
b111 N
b100 +
b11111111111111111111111111111011 (
b0 '
b101 &
b111100011000001111111111111011 )
b1001 *
b111 ;
b10100111001110011100000000000 <
b0 >
1S
#300000
0S
#305000
1H
b10000010000110001000000000000 K
b100 J
b0 "
b10000010000110001000000000000 L
b100 !
b111100011000001111111111111011 #
b100 %
b1010 ?
b1010 -
b111001010000101111111111111110 ,
1R
#310000
0R
#315000
0P
b0 N
b11000110 G
b100 O
b11111111111111111111111111111110 F
b11001000 E
b100 ;
b111100011000001111111111111011 <
b100 >
b11 +
b11111111111111111111111111111110 (
b101010 '
b11001000 &
b111001010000101111111111111110 )
b1010 *
1S
#320000
0S
#325000
0H
b10100111001110011100000000000 K
b101 J
1Q
b101 ?
b101 -
b10000010000110001000000000000 ,
b101010 "
b0 L
b11000110 !
b111001010000101111111111111110 #
b11 %
1R
#330000
0R
#335000
b11010010 G
b10 N
b101 F
b101010 E
b11000110 O
b0 +
b1000000000000 (
b101 '
b101010 &
b10000010000110001000000000000 )
b101 *
b11000110 ;
b111001010000101111111111111110 <
b11 >
1S
#340000
0S
#345000
0M
b101100011000110000000000000001 K
b110 J
b101 "
b11010010 !
b10000010000110001000000000000 #
b0 %
0Q
b110 ?
b110 -
b10100111001110011100000000000 ,
1R
#350000
0R
#355000
1P
b111 G
b11010010 O
b10 N
b111 F
b111 E
b11010010 ;
b10000010000110001000000000000 <
b0 >
b11100000000000 (
b111 '
b111 &
b10100111001110011100000000000 )
b110 *
1S
#360000
0S
#365000
b10100111001110011100000000000 K
b111 J
b11010010 B
b111 ?
b111 -
b101100011000110000000000000001 ,
b111 "
b10100111001110011100000000000 L
b111 !
b10100111001110011100000000000 #
1R
#370000
0R
#375000
b100 G
b111 N
b1 F
b101 E
b111 O
b1 +
b1 (
b101 '
b101 &
b101100011000110000000000000001 )
b111 *
b111 ;
b10100111001110011100000000000 <
1S
#380000
0S
#385000
b111100011000001111111111111011 K
b1000 J
b101 "
b10000010000110001000000000000 L
b100 !
b101100011000110000000000000001 #
b1 %
b1000 ?
b1000 -
b10100111001110011100000000000 ,
1R
#390000
0R
#395000
b11 N
b111 G
b100 O
b111 F
b111 E
b100 ;
b101100011000110000000000000001 <
b1 >
b0 +
b11100000000000 (
b111 '
b111 &
b10100111001110011100000000000 )
b1000 *
1S
#400000
0S
#405000
b111001010000101111111111111110 K
b1001 J
b100 C
b1001 ?
b1001 -
b111100011000001111111111111011 ,
b111 "
b10100111001110011100000000000 L
b111 !
b10100111001110011100000000000 #
b0 %
1R
#410000
0R
#415000
b100 G
1P
b11111111111111111111111111111011 F
b1001 E
b111 O
b111 N
b100 +
b11111111111111111111111111111011 (
b0 '
b100 &
b111100011000001111111111111011 )
b1001 *
b111 ;
b10100111001110011100000000000 <
b0 >
1S
#420000
0S
#425000
1H
b10000010000110001000000000000 K
b100 J
b0 "
b10000010000110001000000000000 L
b100 !
b111100011000001111111111111011 #
b100 %
b1010 ?
b1010 -
b111001010000101111111111111110 ,
1R
#430000
0R
#435000
0P
b0 N
b11000110 G
b100 O
b11111111111111111111111111111110 F
b11001000 E
b100 ;
b111100011000001111111111111011 <
b100 >
b11 +
b11111111111111111111111111111110 (
b11010010 '
b11001000 &
b111001010000101111111111111110 )
b1010 *
1S
#440000
0S
#445000
0H
b10100111001110011100000000000 K
b101 J
1Q
b101 ?
b101 -
b10000010000110001000000000000 ,
b11010010 "
b0 L
b11000110 !
b111001010000101111111111111110 #
b11 %
1R
#450000
0R
#455000
b1101001000 G
b10 N
b100 F
b11010010 E
b11000110 O
b0 +
b1000000000000 (
b100 '
b11010010 &
b10000010000110001000000000000 )
b101 *
b11000110 ;
b111001010000101111111111111110 <
b11 >
1S
#460000
0S
#465000
0M
b101100011000110000000000000001 K
b110 J
b100 "
b1101001000 !
b10000010000110001000000000000 #
b0 %
0Q
b110 ?
b110 -
b10100111001110011100000000000 ,
1R
#470000
0R
#475000
1P
b111 G
b1101001000 O
b10 N
b111 F
b111 E
b1101001000 ;
b10000010000110001000000000000 <
b0 >
b11100000000000 (
b111 '
b111 &
b10100111001110011100000000000 )
b110 *
1S
#480000
0S
#485000
b10100111001110011100000000000 K
b111 J
b1101001000 B
b111 ?
b111 -
b101100011000110000000000000001 ,
b111 "
b10100111001110011100000000000 L
b111 !
b10100111001110011100000000000 #
1R
#490000
0R
#495000
b11 G
b111 N
b1 F
b100 E
b111 O
b1 +
b1 (
b100 '
b100 &
b101100011000110000000000000001 )
b111 *
b111 ;
b10100111001110011100000000000 <
1S
#500000
0S
#505000
b111100011000001111111111111011 K
b1000 J
b100 "
b11 !
b101100011000110000000000000001 #
b1 %
b1000 ?
b1000 -
b10100111001110011100000000000 ,
1R
#510000
0R
#515000
b11 N
b111 G
b11 O
b111 F
b111 E
b11 ;
b101100011000110000000000000001 <
b1 >
b0 +
b11100000000000 (
b111 '
b111 &
b10100111001110011100000000000 )
b1000 *
1S
#520000
0S
#525000
b111001010000101111111111111110 K
b1001 J
b11 C
b1001 ?
b1001 -
b111100011000001111111111111011 ,
b111 "
b111 !
b10100111001110011100000000000 #
b0 %
1R
#530000
0R
#535000
b100 G
1P
b11111111111111111111111111111011 F
b1001 E
b111 O
b111 N
b100 +
b11111111111111111111111111111011 (
b0 '
b11 &
b111100011000001111111111111011 )
b1001 *
b111 ;
b10100111001110011100000000000 <
b0 >
1S
#540000
0S
#545000
1H
b10000010000110001000000000000 K
b100 J
b0 "
b10000010000110001000000000000 L
b100 !
b111100011000001111111111111011 #
b100 %
b1010 ?
b1010 -
b111001010000101111111111111110 ,
1R
#550000
0R
#555000
0P
b0 N
b11000110 G
b100 O
b11111111111111111111111111111110 F
b11001000 E
b100 ;
b111100011000001111111111111011 <
b100 >
b11 +
b11111111111111111111111111111110 (
b1101001000 '
b11001000 &
b111001010000101111111111111110 )
b1010 *
1S
#560000
0S
#565000
0H
b10100111001110011100000000000 K
b101 J
1Q
b101 ?
b101 -
b10000010000110001000000000000 ,
b1101001000 "
b0 L
b11000110 !
b111001010000101111111111111110 #
b11 %
1R
#570000
0R
#575000
b100111011000 G
b10 N
b11 F
b1101001000 E
b11000110 O
b0 +
b1000000000000 (
b11 '
b1101001000 &
b10000010000110001000000000000 )
b101 *
b11000110 ;
b111001010000101111111111111110 <
b11 >
1S
#580000
0S
#585000
0M
b101100011000110000000000000001 K
b110 J
b11 "
bx L
b100111011000 !
b10000010000110001000000000000 #
b0 %
0Q
b110 ?
b110 -
b10100111001110011100000000000 ,
1R
#590000
0R
#595000
1P
b111 G
b100111011000 O
b10 N
b111 F
b111 E
b100111011000 ;
b10000010000110001000000000000 <
b0 >
b11100000000000 (
b111 '
b111 &
b10100111001110011100000000000 )
b110 *
1S
#600000
0S
#605000
b10100111001110011100000000000 K
b111 J
b100111011000 B
b111 ?
b111 -
b101100011000110000000000000001 ,
b111 "
b10100111001110011100000000000 L
b111 !
b10100111001110011100000000000 #
1R
#610000
0R
#615000
b10 G
b111 N
b1 F
b11 E
b111 O
b1 +
b1 (
b11 '
b11 &
b101100011000110000000000000001 )
b111 *
b111 ;
b10100111001110011100000000000 <
1S
#620000
0S
