modellingOftheProcessor/alu.v
`timescale 1ns/1ps
module alu(
    input  wire [5:0]  opcode,
    input  wire [31:0] a,
    input  wire [31:0] b,
    output reg  [31:0] result
);
    // Opcodes
    localparam ADD   = 6'b000000,
               SUB   = 6'b000001,
               AND   = 6'b000010,
               SLT   = 6'b000011,
               MUL   = 6'b000100,
               OR    = 6'b000101,
               ADDI  = 6'b001010,
               SUBI  = 6'b001011,
               SLTI  = 6'b001100,
               LW    = 6'b001101,
               SW    = 6'b001110,
               BNEQZ = 6'b001111,
               BEQZ  = 6'b010000;

    always @* begin
        case (opcode)
            ADD, ADDI, LW, SW, BNEQZ, BEQZ: result = a + b;
            SUB, SUBI:                      result = a - b;
            AND:                            result = a & b;
            OR:                             result = a | b;
            SLT, SLTI:                      result = (a < b) ? 32'd1 : 32'd0;
            MUL:                            result = a * b;
            default:                        result = 32'hxxxxxxxx;
        endcase
    end
endmodule

modellingOftheProcessor/memory_interface.v
`timescale 1ns/1ps
module memory_interface(
    input  wire        clock,
    input  wire [31:0] instr_addr,
    output wire [31:0] instr_out,
    input  wire [31:0] data_addr,
    input  wire [31:0] data_in,
    output wire [31:0] data_out,
    input  wire        data_we
);
    reg [31:0] mem[0:1023];

    integer i;
    initial begin
        for (i = 0; i < 1024; i = i + 1) begin
            mem[i] = 32'd0;
        end
    end

    assign instr_out = mem[instr_addr];
    assign data_out  = mem[data_addr];

    always @(posedge clock) begin
        if (data_we) begin
            mem[data_addr] <= data_in;
        end
    end
endmodule

modellingOftheProcessor/regfile.v
`timescale 1ns/1ps
module regfile(
    input  wire        clock,
    input  wire        we,
    input  wire [4:0]  ra1,
    input  wire [4:0]  ra2,
    input  wire [4:0]  wa,
    input  wire [31:0] wd,
    output wire [31:0] rd1,
    output wire [31:0] rd2
);
    reg [31:0] regs[0:31];

    integer i;
    initial begin
        for (i = 0; i < 32; i = i + 1) begin
            regs[i] = 32'd0;
        end
    end

    assign rd1 = (ra1 == 5'd0) ? 32'd0 : regs[ra1];
    assign rd2 = (ra2 == 5'd0) ? 32'd0 : regs[ra2];

    always @(posedge clock) begin
        if (we && (wa != 5'd0)) begin
            regs[wa] <= wd;
        end
    end
endmodule

modellingOftheProcessor/control_unit.v
`timescale 1ns/1ps
module control_unit(
    input  wire [5:0] opcode,
    output reg  [2:0] instr_type
);
    // Opcodes
    localparam ADD   = 6'b000000,
               SUB   = 6'b000001,
               AND   = 6'b000010,
               SLT   = 6'b000011,
               MUL   = 6'b000100,
               OR    = 6'b000101,
               ADDI  = 6'b001010,
               SUBI  = 6'b001011,
               SLTI  = 6'b001100,
               LW    = 6'b001101,
               SW    = 6'b001110,
               BNEQZ = 6'b001111,
               BEQZ  = 6'b010000,
               HLT   = 6'b111111;

    // Instruction type tags
    localparam RR_ALU = 3'b000,
               RM_ALU = 3'b001,
               LOAD   = 3'b010,
               STORE  = 3'b011,
               BRANCH = 3'b100,
               HALT   = 3'b101;

    always @* begin
        case (opcode)
            ADD, SUB, AND, OR, SLT, MUL: instr_type = RR_ALU;
            ADDI, SUBI, SLTI:            instr_type = RM_ALU;
            LW:                          instr_type = LOAD;
            SW:                          instr_type = STORE;
            BNEQZ, BEQZ:                 instr_type = BRANCH;
            HLT:                         instr_type = HALT;
            default:                     instr_type = HALT;
        endcase
    end
endmodule

modellingOftheProcessor/mips.v
// Simple pipelined MIPS-like processor based on lecture transcript
`timescale 1ns/1ps
module mips(input clock1, input clock2);
    // Program counter
    reg [31:0] PC;

    // IF/ID pipeline registers
    reg [31:0] IF_ID_IR, IF_ID_NPC;

    // ID/EX pipeline registers
    reg [31:0] ID_EX_IR, ID_EX_NPC, ID_EX_A, ID_EX_B, ID_EX_IMM;
    reg [2:0]  ID_EX_type;

    // EX/MEM pipeline registers
    reg [31:0] EX_MEM_IR, EX_MEM_ALUOut, EX_MEM_B;
    reg        EX_MEM_cond;
    reg [2:0]  EX_MEM_type;

    // MEM/WB pipeline registers
    reg [31:0] MEM_WB_IR, MEM_WB_ALUOut, MEM_WB_LMD;
    reg [2:0]  MEM_WB_type;

    // Opcodes
    parameter ADD   = 6'b000000,
              SUB   = 6'b000001,
              AND   = 6'b000010,
              SLT   = 6'b000011,
              MUL   = 6'b000100,
              OR    = 6'b000101,
              ADDI  = 6'b001010,
              SUBI  = 6'b001011,
              SLTI  = 6'b001100,
              LW    = 6'b001101,
              SW    = 6'b001110,
              BNEQZ = 6'b001111,
              BEQZ  = 6'b010000,
              HLT   = 6'b111111;

    // Instruction type tags
    parameter RR_ALU = 3'b000,
              RM_ALU = 3'b001,
              LOAD   = 3'b010,
              STORE  = 3'b011,
              BRANCH = 3'b100,
              HALT   = 3'b101;

    // Control flags
    reg halted, taken_branch;

    // Decode / datapath modules
    wire [2:0]  dec_type;
    wire [31:0] rf_rd1, rf_rd2;

    wire        rf_we;
    wire [4:0]  rf_wa;
    wire [31:0] rf_wd;

    wire        branch_taken;
    wire [31:0] ifetch_addr;
    wire [31:0] instr_word;

    wire        mem_we;
    wire [31:0] mem_data_out;

    wire [31:0] alu_a, alu_b, alu_out;

    control_unit cu(
        .opcode(IF_ID_IR[31:26]),
        .instr_type(dec_type)
    );

    regfile rf(
        .clock(clock1),
        .we(rf_we),
        .ra1(IF_ID_IR[25:21]),
        .ra2(IF_ID_IR[20:16]),
        .wa(rf_wa),
        .wd(rf_wd),
        .rd1(rf_rd1),
        .rd2(rf_rd2)
    );

    memory_interface memory(
        .clock(clock2),
        .instr_addr(ifetch_addr),
        .instr_out(instr_word),
        .data_addr(EX_MEM_ALUOut),
        .data_in(EX_MEM_B),
        .data_out(mem_data_out),
        .data_we(mem_we)
    );

    alu alu_unit(
        .opcode(ID_EX_IR[31:26]),
        .a(alu_a),
        .b(alu_b),
        .result(alu_out)
    );

    assign branch_taken =
        ((EX_MEM_IR[31:26] === BEQZ)  && (EX_MEM_cond === 1'b1)) ||
        ((EX_MEM_IR[31:26] === BNEQZ) && (EX_MEM_cond === 1'b0));

    assign ifetch_addr = branch_taken ? EX_MEM_ALUOut : PC;

    assign alu_a = (ID_EX_type == BRANCH) ? ID_EX_NPC : ID_EX_A;
    assign alu_b = (ID_EX_type == RR_ALU) ? ID_EX_B : ID_EX_IMM;

    assign mem_we = (!halted) && (EX_MEM_type == STORE) && (!taken_branch);

    assign rf_wa = (MEM_WB_type == RR_ALU) ? MEM_WB_IR[15:11] : MEM_WB_IR[20:16];
    assign rf_wd = (MEM_WB_type == LOAD) ? MEM_WB_LMD : MEM_WB_ALUOut;
    assign rf_we =
        (!taken_branch) &&
        ((MEM_WB_type == RR_ALU) || (MEM_WB_type == RM_ALU) || (MEM_WB_type == LOAD)) &&
        (rf_wa != 5'd0);

    initial begin
        PC = 0;
        halted = 0;
        taken_branch = 0;
    end

    // Instruction Fetch
    always @(posedge clock1) begin
        if (!halted) begin
            IF_ID_IR  <= instr_word;
            IF_ID_NPC <= ifetch_addr + 1;
            PC        <= ifetch_addr + 1;
            taken_branch <= branch_taken;
        end
    end

    // Instruction Decode
    always @(posedge clock2) begin
        if (!halted) begin
            ID_EX_NPC <= IF_ID_NPC;
            ID_EX_IR  <= IF_ID_IR;

            // Register operand fetch with R0 hardwired to zero
            ID_EX_A <= rf_rd1;
            ID_EX_B <= rf_rd2;

            // Sign-extended immediate
            ID_EX_IMM <= {{16{IF_ID_IR[15]}}, IF_ID_IR[15:0]};

            // Determine instruction type
            ID_EX_type <= dec_type;
        end
    end

    // Execute
    always @(posedge clock1) begin
        if (!halted) begin
            EX_MEM_type <= ID_EX_type;
            EX_MEM_IR   <= ID_EX_IR;
            EX_MEM_ALUOut <= (ID_EX_type == HALT) ? 32'd0 : alu_out;
            EX_MEM_B      <= ID_EX_B;
            EX_MEM_cond   <= (ID_EX_A == 0);//its checking the condition , here, to branch or not .
        end
    end

    // Memory access
    always @(posedge clock2) begin
        if (!halted) begin
            MEM_WB_type   <= EX_MEM_type;
            MEM_WB_IR     <= EX_MEM_IR;
            MEM_WB_ALUOut <= EX_MEM_ALUOut;

            case (EX_MEM_type)
                LOAD: begin
                    MEM_WB_LMD <= mem_data_out;
                end
                default: ;
            endcase
        end
    end

    // Write back
    always @(posedge clock1) begin
        if (!taken_branch) begin
            case (MEM_WB_type)
                HALT: halted <= 1'b1;
                default: ;
            endcase
        end
    end
endmodule

modellingOftheProcessor/tb_memory_word.v
`timescale 1ns/1ps

module tb_memory_word;
    reg clock1, clock2;
    mips uut(.clock1(clock1), .clock2(clock2));

    integer k;
    reg init_done;

    // Core pipeline/debug signals (flattened into TB scope for clean VCDs).
    wire [31:0] PC = uut.PC;
    wire [31:0] ifetch_addr = uut.ifetch_addr;
    wire [31:0] instr_word = uut.instr_word;

    wire [31:0] IF_ID_IR = uut.IF_ID_IR;
    wire [31:0] IF_ID_NPC = uut.IF_ID_NPC;

    wire [31:0] ID_EX_IR = uut.ID_EX_IR;
    wire [31:0] ID_EX_NPC = uut.ID_EX_NPC;
    wire [31:0] ID_EX_A = uut.ID_EX_A;
    wire [31:0] ID_EX_B = uut.ID_EX_B;
    wire [31:0] ID_EX_IMM = uut.ID_EX_IMM;
    wire [2:0]  ID_EX_type = uut.ID_EX_type;

    wire [31:0] alu_a = uut.alu_a;
    wire [31:0] alu_b = uut.alu_b;
    wire [31:0] alu_out = uut.alu_out;

    wire [31:0] EX_MEM_IR = uut.EX_MEM_IR;
    wire [31:0] EX_MEM_ALUOut = uut.EX_MEM_ALUOut;
    wire [31:0] EX_MEM_B = uut.EX_MEM_B;
    wire        EX_MEM_cond = uut.EX_MEM_cond;
    wire [2:0]  EX_MEM_type = uut.EX_MEM_type;

    wire        mem_we = uut.mem_we;
    wire [31:0] mem_data_out = uut.mem_data_out;

    wire [31:0] MEM_WB_IR = uut.MEM_WB_IR;
    wire [31:0] MEM_WB_ALUOut = uut.MEM_WB_ALUOut;
    wire [31:0] MEM_WB_LMD = uut.MEM_WB_LMD;
    wire [2:0]  MEM_WB_type = uut.MEM_WB_type;

    wire        rf_we = uut.rf_we;
    wire [4:0]  rf_wa = uut.rf_wa;
    wire [31:0] rf_wd = uut.rf_wd;

    wire        branch_taken = uut.branch_taken;
    wire        taken_branch = uut.taken_branch;
    wire        halted = uut.halted;

    // Waveform-friendly aliases (avoid dumping array elements directly).
    wire [31:0] R0 = uut.rf.regs[0];
    wire [31:0] R1 = uut.rf.regs[1];
    wire [31:0] R2 = uut.rf.regs[2];
    wire [31:0] R3 = uut.rf.regs[3];

    wire [31:0] IMEM0 = uut.memory.mem[0];
    wire [31:0] IMEM1 = uut.memory.mem[1];
    wire [31:0] IMEM2 = uut.memory.mem[2];
    wire [31:0] IMEM3 = uut.memory.mem[3];
    wire [31:0] IMEM4 = uut.memory.mem[4];
    wire [31:0] IMEM5 = uut.memory.mem[5];
    wire [31:0] IMEM6 = uut.memory.mem[6];
    wire [31:0] IMEM7 = uut.memory.mem[7];

    wire [31:0] MEM120 = uut.memory.mem[120];
    wire [31:0] MEM121 = uut.memory.mem[121];

    initial begin
        clock1 = 0; clock2 = 0;
        wait (init_done);
        repeat (60) begin
            #5 clock1 = 1; #5 clock1 = 0;
            #5 clock2 = 1; #5 clock2 = 0;
        end
    end

    initial begin
        init_done = 0;
        #0;
        // Initialize registers
        for (k = 0; k < 32; k = k + 1) begin
            uut.rf.regs[k] = k;
        end

        // Sample program demonstrating load/add/store
        uut.memory.mem[0] = 32'h28010078; // ADDI R1, R0, 120
        uut.memory.mem[1] = 32'h14631800; // OR R3, R3, R3 (dummy)
        uut.memory.mem[2] = 32'h34220000; // LW  R2, 0(R1)
        uut.memory.mem[3] = 32'h14631800; // OR R3, R3, R3 (dummy)
        uut.memory.mem[4] = 32'h2842002d; // ADDI R2, R2, 45
        uut.memory.mem[5] = 32'h14631800; // OR R3, R3, R3 (dummy)
        uut.memory.mem[6] = 32'h38220001; // SW R2, 1(R1)
        uut.memory.mem[7] = 32'hfc000000; // HLT

        // Preload memory[120] with a value
        uut.memory.mem[120] = 32'd85;

        // Reset control flags and PC
        uut.PC = 0; uut.halted = 0; uut.taken_branch = 0;

        // Initialize pipeline regs for cleaner waveforms (avoids X-propagation).
        uut.IF_ID_IR = 0; uut.IF_ID_NPC = 0;
        uut.ID_EX_IR = 0; uut.ID_EX_NPC = 0; uut.ID_EX_A = 0; uut.ID_EX_B = 0; uut.ID_EX_IMM = 0; uut.ID_EX_type = 0;
        uut.EX_MEM_IR = 0; uut.EX_MEM_ALUOut = 0; uut.EX_MEM_B = 0; uut.EX_MEM_cond = 0; uut.EX_MEM_type = 0;
        uut.MEM_WB_IR = 0; uut.MEM_WB_ALUOut = 0; uut.MEM_WB_LMD = 0; uut.MEM_WB_type = 0;

        init_done = 1;

        #600;
        $display("Mem[120]: %0d", uut.memory.mem[120]);
        $display("Mem[121]: %0d", uut.memory.mem[121]);
        $finish;
    end

    initial begin
        wait (init_done);
        $dumpfile("tb_memory_word.vcd");
        $dumpvars(1, tb_memory_word);
    end
endmodule

modellingOftheProcessor/artifacts/tb_memory_word.vcd
$date
	Mon Feb 02 06:53:20 2026
$end
$version
	Icarus Verilog
$end
$timescale
	1ps
$end
$scope module tb_memory_word $end
$var wire 32 ! EX_MEM_ALUOut [31:0] $end
$var wire 32 " EX_MEM_B [31:0] $end
$var wire 32 # EX_MEM_IR [31:0] $end
$var wire 1 $ EX_MEM_cond $end
$var wire 3 % EX_MEM_type [2:0] $end
$var wire 32 & ID_EX_A [31:0] $end
$var wire 32 ' ID_EX_B [31:0] $end
$var wire 32 ( ID_EX_IMM [31:0] $end
$var wire 32 ) ID_EX_IR [31:0] $end
$var wire 32 * ID_EX_NPC [31:0] $end
$var wire 3 + ID_EX_type [2:0] $end
$var wire 32 , IF_ID_IR [31:0] $end
$var wire 32 - IF_ID_NPC [31:0] $end
$var wire 32 . IMEM0 [31:0] $end
$var wire 32 / IMEM1 [31:0] $end
$var wire 32 0 IMEM2 [31:0] $end
$var wire 32 1 IMEM3 [31:0] $end
$var wire 32 2 IMEM4 [31:0] $end
$var wire 32 3 IMEM5 [31:0] $end
$var wire 32 4 IMEM6 [31:0] $end
$var wire 32 5 IMEM7 [31:0] $end
$var wire 32 6 MEM120 [31:0] $end
$var wire 32 7 MEM121 [31:0] $end
$var wire 32 8 MEM_WB_ALUOut [31:0] $end
$var wire 32 9 MEM_WB_IR [31:0] $end
$var wire 32 : MEM_WB_LMD [31:0] $end
$var wire 3 ; MEM_WB_type [2:0] $end
$var wire 32 < PC [31:0] $end
$var wire 32 = R0 [31:0] $end
$var wire 32 > R1 [31:0] $end
$var wire 32 ? R2 [31:0] $end
$var wire 32 @ R3 [31:0] $end
$var wire 32 A alu_a [31:0] $end
$var wire 32 B alu_b [31:0] $end
$var wire 32 C alu_out [31:0] $end
$var wire 1 D branch_taken $end
$var wire 1 E halted $end
$var wire 32 F ifetch_addr [31:0] $end
$var wire 32 G instr_word [31:0] $end
$var wire 32 H mem_data_out [31:0] $end
$var wire 1 I mem_we $end
$var wire 5 J rf_wa [4:0] $end
$var wire 32 K rf_wd [31:0] $end
$var wire 1 L rf_we $end
$var wire 1 M taken_branch $end
$var reg 1 N clock1 $end
$var reg 1 O clock2 $end
$var reg 1 P init_done $end
$var integer 32 Q k [31:0] $end
$upscope $end
$enddefinitions $end
$comment Show the parameter values. $end
$dumpall
$end
#0
$dumpvars
b100000 Q
1P
0O
0N
0M
0L
b0 K
b0 J
0I
b101000000000010000000001111000 H
b101000000000010000000001111000 G
b0 F
0E
0D
b0 C
b0 B
b0 A
b11 @
b10 ?
b1 >
b0 =
b0 <
b0 ;
b0 :
b0 9
b0 8
b0 7
b1010101 6
b11111100000000000000000000000000 5
b111000001000100000000000000001 4
b10100011000110001100000000000 3
b101000010000100000000000101101 2
b10100011000110001100000000000 1
b110100001000100000000000000000 0
b10100011000110001100000000000 /
b101000000000010000000001111000 .
b0 -
b0 ,
b0 +
b0 *
b0 )
b0 (
b0 '
b0 &
b0 %
0$
b0 #
b0 "
b0 !
$end
#5000
b10100011000110001100000000000 G
b1 F
b1 <
b1 -
b101000000000010000000001111000 ,
1$
1N
#10000
0N
#15000
b1111000 C
b1111000 B
b1 +
b1111000 (
b1 '
b101000000000010000000001111000 )
b1 *
1O
#20000
0O
#25000
b110100001000100000000000000000 G
b10 F
b1 "
b1010101 H
b1111000 !
b101000000000010000000001111000 #
b1 %
b10 <
b10 -
b10100011000110001100000000000 ,
1N
#30000
0N
#35000
1L
b1 J
b11 C
b1111000 K
b11 B
b11 A
b1111000 8
b101000000000010000000001111000 9
b1 ;
b0 +
b1100000000000 (
b11 '
b11 &
b10100011000110001100000000000 )
b10 *
1O
#40000
0O
#45000
b10100011000110001100000000000 G
b11 F
b1111000 >
b11 <
b11 -
b110100001000100000000000000000 ,
0$
b11 "
b10100011000110001100000000000 H
b11 !
b10100011000110001100000000000 #
b0 %
1N
#50000
0N
#55000
b1111000 C
1L
b0 B
b1111000 A
b11 K
b11 J
b10 +
b0 (
b10 '
b1111000 &
b110100001000100000000000000000 )
b11 *
b11 8
b10100011000110001100000000000 9
b0 ;
1O
#60000
0O
#65000
b101000010000100000000000101101 G
b100 F
b10 "
b1010101 H
b1111000 !
b110100001000100000000000000000 #
b10 %
b100 <
b100 -
b10100011000110001100000000000 ,
1N
#70000
0N
#75000
b10 J
b11 C
b1010101 K
b11 B
b11 A
b1010101 :
b1111000 8
b110100001000100000000000000000 9
b10 ;
b0 +
b1100000000000 (
b11 '
b11 &
b10100011000110001100000000000 )
b100 *
1O
#80000
0O
#85000
b10100011000110001100000000000 G
b101 F
b1010101 ?
b101 <
b101 -
b101000010000100000000000101101 ,
b11 "
b10100011000110001100000000000 H
b11 !
b10100011000110001100000000000 #
b0 %
1N
#90000
0N
#95000
b10000010 C
1L
b101101 B
b1010101 A
b11 J
b11 K
b1 +
b101101 (
b1010101 '
b1010101 &
b101000010000100000000000101101 )
b101 *
b11 8
b10100011000110001100000000000 9
b0 ;
1O
#100000
0O
#105000
b111000001000100000000000000001 G
b110 F
b1010101 "
b0 H
b10000010 !
b101000010000100000000000101101 #
b1 %
b110 <
b110 -
b10100011000110001100000000000 ,
1N
#110000
0N
#115000
b10 J
b11 C
b10000010 K
b11 B
b11 A
b10000010 8
b101000010000100000000000101101 9
b1 ;
b0 +
b1100000000000 (
b11 '
b11 &
b10100011000110001100000000000 )
b110 *
1O
#120000
0O
#125000
b11111100000000000000000000000000 G
b111 F
b10000010 ?
b111 <
b111 -
b111000001000100000000000000001 ,
b11 "
b10100011000110001100000000000 H
b11 !
b10100011000110001100000000000 #
b0 %
1N
#130000
0N
#135000
b1111001 C
1L
b1 B
b1111000 A
b11 K
b11 J
b11 +
b1 (
b10000010 '
b1111000 &
b111000001000100000000000000001 )
b111 *
b11 8
b10100011000110001100000000000 9
b0 ;
1O
#140000
0O
#145000
1I
b0 G
b1000 F
b10000010 "
b0 H
b1111001 !
b111000001000100000000000000001 #
b11 %
b1000 <
b1000 -
b11111100000000000000000000000000 ,
1N
#150000
0N
#155000
0L
b10 J
bx C
b1111001 K
b0 B
b0 A
b1111001 8
b111000001000100000000000000001 9
b11 ;
b101 +
b0 (
b0 '
b0 &
b11111100000000000000000000000000 )
b1000 *
b10000010 H
b10000010 7
1O
#160000
0O
#165000
0I
b1001 F
b1001 <
b1001 -
b0 ,
1$
b0 "
b101000000000010000000001111000 H
b0 !
b11111100000000000000000000000000 #
b101 %
1N
#170000
0N
#175000
b0 C
b0 J
b0 K
b0 +
b0 )
b1001 *
b0 8
b11111100000000000000000000000000 9
b101 ;
1O
#180000
0O
#185000
b1010 F
1E
b0 #
b0 %
b1010 <
b1010 -
1N
